TimeSeriesPy/__init__.py
TimeSeriesPy/test.py
TimeSeriesPy-0.0.1.dist-info/LICENSE
TimeSeriesPy-0.0.1.dist-info/METADATA
TimeSeriesPy-0.0.1.dist-info/WHEEL
TimeSeriesPy-0.0.1.dist-info/top_level.txt
TimeSeriesPy-0.0.1.dist-info/RECORD
