Metadata-Version: 2.1
Name: TimeSeriesPy
Version: 0.0.1
Summary: A package for time series forecasting.
Home-page: https://github.com/FabioScielzoOrtiz/TimeSeriesPy_Package
Author: Fabio Scielzo Ortiz
Author-email: fabioscielzo98@gmail.com
Classifier: Programming Language :: Python :: 3
Classifier: License :: OSI Approved :: MIT License
Classifier: Operating System :: OS Independent
Requires-Python: >=3.7
License-File: LICENSE
Requires-Dist: pandas
Requires-Dist: numpy
